teachbooks_sphinx_thebe/__init__.py
teachbooks_sphinx_thebe/_version.py
teachbooks_sphinx_thebe/_static/_hook_fetch_module_finder.py
teachbooks_sphinx_thebe/_static/code.css
teachbooks_sphinx_thebe/_static/play-solid.svg
teachbooks_sphinx_thebe/_static/refresh.js
teachbooks_sphinx_thebe/_static/sphinx-thebe-lite.js
teachbooks_sphinx_thebe/_static/sphinx-thebe.css
teachbooks_sphinx_thebe/_static/sphinx-thebe.js
teachbooks_sphinx_thebe/_thebe_static/.gitkeep
teachbooks_sphinx_thebe/_thebe_static/1078.index.js
teachbooks_sphinx_thebe/_thebe_static/1078.index.js.map
teachbooks_sphinx_thebe/_thebe_static/1118.index.js
teachbooks_sphinx_thebe/_thebe_static/1118.index.js.map
teachbooks_sphinx_thebe/_thebe_static/1327.index.js
teachbooks_sphinx_thebe/_thebe_static/1327.index.js.map
teachbooks_sphinx_thebe/_thebe_static/1363.index.js
teachbooks_sphinx_thebe/_thebe_static/1363.index.js.map
teachbooks_sphinx_thebe/_thebe_static/1620.index.js
teachbooks_sphinx_thebe/_thebe_static/1620.index.js.map
teachbooks_sphinx_thebe/_thebe_static/1643.index.js
teachbooks_sphinx_thebe/_thebe_static/1643.index.js.map
teachbooks_sphinx_thebe/_thebe_static/1649.index.js
teachbooks_sphinx_thebe/_thebe_static/1649.index.js.map
teachbooks_sphinx_thebe/_thebe_static/1711.index.js
teachbooks_sphinx_thebe/_thebe_static/1711.index.js.map
teachbooks_sphinx_thebe/_thebe_static/1757.index.js
teachbooks_sphinx_thebe/_thebe_static/1757.index.js.map
teachbooks_sphinx_thebe/_thebe_static/1803.index.js
teachbooks_sphinx_thebe/_thebe_static/1803.index.js.map
teachbooks_sphinx_thebe/_thebe_static/1814.index.js
teachbooks_sphinx_thebe/_thebe_static/1814.index.js.map
teachbooks_sphinx_thebe/_thebe_static/192.index.js
teachbooks_sphinx_thebe/_thebe_static/192.index.js.map
teachbooks_sphinx_thebe/_thebe_static/2123.index.js
teachbooks_sphinx_thebe/_thebe_static/2123.index.js.map
teachbooks_sphinx_thebe/_thebe_static/2155.index.js
teachbooks_sphinx_thebe/_thebe_static/2155.index.js.map
teachbooks_sphinx_thebe-1.0.2.dist-info/METADATA
teachbooks_sphinx_thebe-1.0.2.dist-info/WHEEL
teachbooks_sphinx_thebe-1.0.2.dist-info/licenses/LICENSE
teachbooks_sphinx_thebe-1.0.2.dist-info/RECORD
